[
  {"name": "Aurora Desk Lamp", "description": "Warm-white LED desk lamp with dimmer", "price_cents": 4200, "category": "home", "stock": 25},
  {"name": "Linen Throw Blanket", "description": "Stonewashed linen, 130x170cm", "price_cents": 5400, "category": "home", "stock": 18},
  {"name": "Ceramic Pour-Over Set", "description": "Dripper and carafe for pour-over coffee", "price_cents": 3600, "category": "home", "stock": 30},
  {"name": "Trailhead Backpack", "description": "28L weatherproof daypack", "price_cents": 8900, "category": "outdoor", "stock": 12},
  {"name": "Summit Water Bottle", "description": "1L insulated stainless steel bottle", "price_cents": 2900, "category": "outdoor", "stock": 50},
  {"name": "Pocket Rain Shell", "description": "Packable waterproof jacket", "price_cents": 7400, "category": "outdoor", "stock": 20},
  {"name": "Espresso Beans 1kg", "description": "Single-origin medium roast coffee", "price_cents": 1800, "category": "grocery", "stock": 60},
  {"name": "Cold Brew Concentrate", "description": "Smooth coffee concentrate, 500ml", "price_cents": 1200, "category": "grocery", "stock": 45},
  {"name": "Dark Chocolate Bar", "description": "70% cacao, single estate", "price_cents": 600, "category": "grocery", "stock": 120},
  {"name": "Mechanical Keyboard", "description": "Hot-swappable, tactile switches", "price_cents": 11900, "category": "electronics", "stock": 8},
  {"name": "Wireless Mouse", "description": "Ergonomic, silent-click", "price_cents": 3900, "category": "electronics", "stock": 35},
  {"name": "USB-C Hub", "description": "7-in-1 multiport adapter", "price_cents": 4900, "category": "electronics", "stock": 28},
  {"name": "Noise-Cancelling Earbuds", "description": "ANC earbuds with charging case", "price_cents": 9900, "category": "electronics", "stock": 15},
  {"name": "Standing Desk Mat", "description": "Anti-fatigue cushioned mat", "price_cents": 4500, "category": "home", "stock": 22},
  {"name": "Cast Iron Skillet", "description": "Pre-seasoned 26cm skillet", "price_cents": 3300, "category": "home", "stock": 40},
  {"name": "Merino Wool Socks", "description": "3-pack, cushioned hiking socks", "price_cents": 2400, "category": "outdoor", "stock": 70},
  {"name": "Trail Running Shoes", "description": "Grippy, breathable trail runners", "price_cents": 12900, "category": "outdoor", "stock": 10},
  {"name": "Matcha Tin 100g", "description": "Ceremonial-grade green tea powder", "price_cents": 2700, "category": "grocery", "stock": 38},
  {"name": "Olive Oil 750ml", "description": "Cold-pressed extra virgin", "price_cents": 1500, "category": "grocery", "stock": 55},
  {"name": "Notebook 3-Pack", "description": "Dotted A5 notebooks", "price_cents": 1900, "category": "stationery", "stock": 80},
  {"name": "Fountain Pen", "description": "Fine-nib, refillable ink", "price_cents": 3200, "category": "stationery", "stock": 26},
  {"name": "Desk Organizer", "description": "Bamboo multi-slot organizer", "price_cents": 2800, "category": "stationery", "stock": 33},
  {"name": "LED Monitor Light Bar", "description": "Screen-mounted task light", "price_cents": 5900, "category": "electronics", "stock": 19},
  {"name": "Travel Coffee Mug", "description": "Leakproof 350ml mug", "price_cents": 2100, "category": "home", "stock": 64}
]
